taiji_hasp/__init__.py
taiji_hasp/libhasp_linux_x86_64_68851.so
taiji_hasp/taiji_hasp.cpython-310-x86_64-linux-gnu.so
taiji_hasp-0.1.3.dist-info/METADATA
taiji_hasp-0.1.3.dist-info/WHEEL
taiji_hasp-0.1.3.dist-info/top_level.txt
taiji_hasp-0.1.3.dist-info/RECORD
