Metadata-Version: 2.1
Name: taiji-hasp
Version: 0.1.3
Summary: A Python wrapper for HASP license protection
Author: kkzhang
Author-email: kkzhang3@hotmail.com
Classifier: Programming Language :: Python :: 3
Classifier: License :: OSI Approved :: MIT License
Classifier: Operating System :: Microsoft :: Windows
Classifier: Operating System :: POSIX :: Linux
Requires-Python: >=3.6
